README.md
setup.py
pydemonstrativos/cvm.py
pydemonstrativos.egg-info/PKG-INFO
pydemonstrativos.egg-info/SOURCES.txt
pydemonstrativos.egg-info/dependency_links.txt
pydemonstrativos.egg-info/requires.txt
pydemonstrativos.egg-info/top_level.txt