Metadata-Version: 2.1
Name: pydemonstrativos
Version: 0.0.3
Summary: Demonstrativos Financeiros - Dados CVM
Home-page: https://github.com/andremsilveira/pydemonstrativos
Author: Andre Silveira
Author-email: andre.a.silveira@icloud.com
License: MIT License
Keywords: Pacote
Platform: UNKNOWN
